ctyun/bootstrap/__init__.py
ctyun/bootstrap/bootstrap_gen.py
ctyun/bootstrap/py.typed
ctyun/bootstrap/utils.py
ctyun/bootstrap/version.py
ctyun_bootstrap-1.3.0.dist-info/METADATA
ctyun_bootstrap-1.3.0.dist-info/WHEEL
ctyun_bootstrap-1.3.0.dist-info/entry_points.txt
ctyun_bootstrap-1.3.0.dist-info/licenses/LICENSE
ctyun_bootstrap-1.3.0.dist-info/RECORD
