Metadata-Version: 2.4
Name: ctyun-bootstrap
Version: 1.3.0
Summary: ctyun  bootstrap 
Project-URL: Homepage, https://github.com/open-telemetry/opentelemetry-python-contrib/tree/main/opentelemetry-instrumentation
Author: ctyun Authors
License: Apache-2.0
License-File: LICENSE
Classifier: Development Status :: 4 - Beta
Classifier: Intended Audience :: Developers
Classifier: License :: OSI Approved :: Apache Software License
Classifier: Programming Language :: Python
Classifier: Programming Language :: Python :: 3
Classifier: Programming Language :: Python :: 3.8
Classifier: Programming Language :: Python :: 3.9
Classifier: Programming Language :: Python :: 3.10
Classifier: Programming Language :: Python :: 3.11
Classifier: Programming Language :: Python :: 3.12
Requires-Python: >=3.8
Requires-Dist: requests
Requires-Dist: setuptools>=16.0
Requires-Dist: wrapt<2.0.0,>=1.0.0
